packagetracker/__init__.py
packagetracker/package.py
packagetracker-1.0.dist-info/LICENSE
packagetracker-1.0.dist-info/METADATA
packagetracker-1.0.dist-info/WHEEL
packagetracker-1.0.dist-info/top_level.txt
packagetracker-1.0.dist-info/RECORD
